pytorch_cnn_trainer/__init__.py
pytorch_cnn_trainer/dataset.py
pytorch_cnn_trainer/engine.py
pytorch_cnn_trainer/lightning_trainer.py
pytorch_cnn_trainer/model_factory.py
pytorch_cnn_trainer/plotter.py
pytorch_cnn_trainer/utils.py
pytorch_cnn_trainer-0.3.0.dist-info/LICENSE
pytorch_cnn_trainer-0.3.0.dist-info/METADATA
pytorch_cnn_trainer-0.3.0.dist-info/WHEEL
pytorch_cnn_trainer-0.3.0.dist-info/entry_points.txt
pytorch_cnn_trainer-0.3.0.dist-info/top_level.txt
pytorch_cnn_trainer-0.3.0.dist-info/RECORD
