Metadata-Version: 2.1
Name: pytorch-cnn-trainer
Version: 0.3.0
Summary: A simple yet powerful CNN trainer for PyTorch and Lightning.
Home-page: https://github.com/oke-aditya/pytorch_cnn_trainer/tree/master/
Author: Aditya Oke
Author-email: okeaditya315@gmail.com
License: Apache Software License 2.0
Keywords: PyTorch
Platform: UNKNOWN
Classifier: Development Status :: 3 - Alpha
Classifier: Intended Audience :: Developers
Classifier: License :: OSI Approved :: Apache Software License
Classifier: Natural Language :: English
Classifier: Programming Language :: Python :: 3.6
Classifier: Programming Language :: Python :: 3.7
Classifier: Programming Language :: Python :: 3.8
Requires-Python: >=3.6
Requires-Dist: tqdm
Requires-Dist: timm
Requires-Dist: matplotlib
Requires-Dist: pytorch-lightning
